<?xml version="1.0" encoding="utf-16"?>
<CaptureVerificationActivityForm xmlns:xsd="http://www.w3.org/2001/XMLSchema" xmlns:xsi="http://www.w3.org/2001/XMLSchema-instance">
  <DBVersion>7.10</DBVersion>
  <FormType>CaptureVerificationActivityForm</FormType>
  <FormIdentity>
    <Id>BE9F56EA0F3D47EB8ACE375A258B9C38</Id>
    <AutomaticallyPopulate>false</AutomaticallyPopulate>
    <Name>t11_Verification</Name>
    <Version>1</Version>
  </FormIdentity>
  <Title>t11_Verification</Title>
  <Width>1300</Width>
  <Height>680</Height>
  <LastModifiedDateTime>2021-07-23T19:02:36.763</LastModifiedDateTime>
  <InternalModifiedDate>2021-07-23T19:02:36.763</InternalModifiedDate>
  <LastModifiedByUser>EF125000ED0B4FDDA1E4CE6343503603</LastModifiedByUser>
  <Columns>
    <FormColumn>
      <DisplayIndex>0</DisplayIndex>
      <Width>1300</Width>
      <PercentageWidth>100</PercentageWidth>
      <Height>680</Height>
      <Rows>
        <Row>
          <Width>1300</Width>
          <Height>20</Height>
          <DisplayIndex>0</DisplayIndex>
          <Cells>
            <Cell>
              <Id>B49D2342D884466C81470744D47F6C62</Id>
              <Name>Cell1</Name>
              <Collapsible>false</Collapsible>
              <Collapsed>false</Collapsed>
              <Visible>true</Visible>
              <DisplayIndex>0</DisplayIndex>
              <Width>1300</Width>
              <PercentageWidth>100</PercentageWidth>
              <CellLayout>1</CellLayout>
              <Height>680</Height>
              <MinHeight>25</MinHeight>
              <Orientation>1</Orientation>
              <Border>0</Border>
              <BackgroundColor>Transparent</BackgroundColor>
              <CellControls>
                <FormControl xsi:type="VerificationCaptureControl">
                  <ControlType>CaptureVerification</ControlType>
                  <FormControlEvents>
                    <FormEvent>
                      <EventType>OnSelectDocument</EventType>
                      <Actions />
                    </FormEvent>
                    <FormEvent>
                      <EventType>OnSelectFolder</EventType>
                      <Actions />
                    </FormEvent>
                    <FormEvent>
                      <EventType>OnSaveFieldChanges</EventType>
                      <Actions>
                        <FormActionSummary>
                          <Identity>
                            <Id>F86DFE516EBB456DA1F46A438758485D</Id>
                            <Name>VerificationControlSaveChanges</Name>
                            <ActionType>DotNet</ActionType>
                          </Identity>
                          <Disabled>false</Disabled>
                        </FormActionSummary>
                      </Actions>
                    </FormEvent>
                    <FormEvent>
                      <EventType>OnCaptureCancelActivity</EventType>
                      <Actions>
                        <FormActionSummary>
                          <Identity>
                            <Id>E3D7BC472766474A9A9278882002D71E</Id>
                            <Name>VerificationControlUnloadBatchCancelAction</Name>
                            <ActionType>DotNet</ActionType>
                          </Identity>
                          <Disabled>false</Disabled>
                        </FormActionSummary>
                        <FormActionSummary>
                          <Identity>
                            <Id>50F0645B4B7245628A8E751D3410DF57</Id>
                            <Name>cancelactivity</Name>
                            <ActionType>DotNet</ActionType>
                          </Identity>
                          <Disabled>false</Disabled>
                        </FormActionSummary>
                        <FormActionSummary>
                          <Identity>
                            <Id>38E67CF21C614D6CB82A2DA37F12C62B</Id>
                            <Name>redirCancel</Name>
                            <ActionType>Redirect</ActionType>
                          </Identity>
                          <Disabled>false</Disabled>
                        </FormActionSummary>
                      </Actions>
                    </FormEvent>
                    <FormEvent>
                      <EventType>OnCaptureCompleteActivity</EventType>
                      <Actions>
                        <FormActionSummary>
                          <Identity>
                            <Id>4B51110B90AD4B54B557342DCF2ED50E</Id>
                            <Name>VerificationControlUnloadBatchCompleteAction</Name>
                            <ActionType>DotNet</ActionType>
                          </Identity>
                          <Disabled>false</Disabled>
                        </FormActionSummary>
                        <FormActionSummary>
                          <Identity>
                            <Id>AE48645C345C49B384BAE0BC406674B4</Id>
                            <Name>activitycomplete</Name>
                            <ActionType>DotNet</ActionType>
                          </Identity>
                          <Disabled>false</Disabled>
                        </FormActionSummary>
                        <FormActionSummary>
                          <Identity>
                            <Id>38E67CF21C614D6CB82A2DA37F12C62B</Id>
                            <Name>redirCancel</Name>
                            <ActionType>Redirect</ActionType>
                          </Identity>
                          <Disabled>false</Disabled>
                        </FormActionSummary>
                        <FormActionSummary>
                          <Identity>
                            <Id>8B39D9612F124A16B0E636BEF1C77FF7</Id>
                            <Name>SamePageEvent1</Name>
                            <ActionType>SamePage</ActionType>
                          </Identity>
                          <Disabled>false</Disabled>
                        </FormActionSummary>
                      </Actions>
                    </FormEvent>
                    <FormEvent>
                      <EventType>OnCaptureCompleteAndTakeNextActivity</EventType>
                      <Actions>
                        <FormActionSummary>
                          <Identity>
                            <Id>4B51110B90AD4B54B557342DCF2ED50E</Id>
                            <Name>VerificationControlUnloadBatchCompleteAction</Name>
                            <ActionType>DotNet</ActionType>
                          </Identity>
                          <Disabled>false</Disabled>
                        </FormActionSummary>
                        <FormActionSummary>
                          <Identity>
                            <Id>AE48645C345C49B384BAE0BC406674B4</Id>
                            <Name>activitycomplete</Name>
                            <ActionType>DotNet</ActionType>
                          </Identity>
                          <Disabled>false</Disabled>
                        </FormActionSummary>
                        <FormActionSummary>
                          <Identity>
                            <Id>6D4E0D544AE644F7ADFCC0AAFCC017DD</Id>
                            <Name>TakeNextActivity</Name>
                            <ActionType>DotNet</ActionType>
                          </Identity>
                          <Disabled>false</Disabled>
                        </FormActionSummary>
                        <FormActionSummary>
                          <Identity>
                            <Id>F436586C01A54915B595EB26037CE7E2</Id>
                            <Name>beginFoundNextAction</Name>
                            <ActionType>BeginCondition</ActionType>
                          </Identity>
                          <Disabled>false</Disabled>
                        </FormActionSummary>
                        <FormActionSummary>
                          <Identity>
                            <Id>50EEEDB8F2324AFB84D94488AC1D87EA</Id>
                            <Name>beginNextAssociatedFileFound</Name>
                            <ActionType>BeginCondition</ActionType>
                          </Identity>
                          <Disabled>false</Disabled>
                        </FormActionSummary>
                        <FormActionSummary>
                          <Identity>
                            <Id>406CB4C8F41C447487211A0536879E25</Id>
                            <Name>redirNextActivity</Name>
                            <ActionType>Redirect</ActionType>
                          </Identity>
                          <Disabled>false</Disabled>
                        </FormActionSummary>
                        <FormActionSummary>
                          <Identity>
                            <Id>E1BFF82903874C48843D2A8BAC1014B2</Id>
                            <Name>endNextAssociatedFileFound</Name>
                            <ActionType>EndCondition</ActionType>
                          </Identity>
                          <Disabled>false</Disabled>
                        </FormActionSummary>
                        <FormActionSummary>
                          <Identity>
                            <Id>B2B7E2B42C0C486FA9113FBE603BC4C3</Id>
                            <Name>beginNextAssociatedFileNotFound</Name>
                            <ActionType>BeginCondition</ActionType>
                          </Identity>
                          <Disabled>false</Disabled>
                        </FormActionSummary>
                        <FormActionSummary>
                          <Identity>
                            <Id>34471E2BF07B428AA3BA8608AE920057</Id>
                            <Name>redirectToGenericTakeActivity</Name>
                            <ActionType>Redirect</ActionType>
                          </Identity>
                          <Disabled>false</Disabled>
                        </FormActionSummary>
                        <FormActionSummary>
                          <Identity>
                            <Id>A0D4DF3805894E688F15A64273F7C982</Id>
                            <Name>endNextAssociatedFileNotFound</Name>
                            <ActionType>EndCondition</ActionType>
                          </Identity>
                          <Disabled>false</Disabled>
                        </FormActionSummary>
                        <FormActionSummary>
                          <Identity>
                            <Id>B4A67EF520C14B338BDA3E6CA919C3FE</Id>
                            <Name>endFoundNextAction</Name>
                            <ActionType>EndCondition</ActionType>
                          </Identity>
                          <Disabled>false</Disabled>
                        </FormActionSummary>
                        <FormActionSummary>
                          <Identity>
                            <Id>FD7D76BA356D4CF0B178062B2759CABB</Id>
                            <Name>beginNextActivityNotFound</Name>
                            <ActionType>BeginCondition</ActionType>
                          </Identity>
                          <Disabled>false</Disabled>
                        </FormActionSummary>
                        <FormActionSummary>
                          <Identity>
                            <Id>38E67CF21C614D6CB82A2DA37F12C62B</Id>
                            <Name>redirCancel</Name>
                            <ActionType>Redirect</ActionType>
                          </Identity>
                          <Disabled>false</Disabled>
                        </FormActionSummary>
                        <FormActionSummary>
                          <Identity>
                            <Id>8B39D9612F124A16B0E636BEF1C77FF7</Id>
                            <Name>SamePageEvent1</Name>
                            <ActionType>SamePage</ActionType>
                          </Identity>
                          <Disabled>false</Disabled>
                        </FormActionSummary>
                        <FormActionSummary>
                          <Identity>
                            <Id>9A476CDFCDCE42A6BB6E3247C19247DC</Id>
                            <Name>endNextActivityNotFound</Name>
                            <ActionType>EndCondition</ActionType>
                          </Identity>
                          <Disabled>false</Disabled>
                        </FormActionSummary>
                      </Actions>
                    </FormEvent>
                    <FormEvent>
                      <EventType>OnCaptureOpenActivity</EventType>
                      <Actions />
                    </FormEvent>
                    <FormEvent>
                      <EventType>OnCaptureSaveActivity</EventType>
                      <Actions />
                    </FormEvent>
                    <FormEvent>
                      <EventType>OnRejectDocuments</EventType>
                      <Actions>
                        <FormActionSummary>
                          <Identity>
                            <Id>EB6360B97F5846B88F266FC87E699E36</Id>
                            <Name>VerificationControlRejectDocumentsAction</Name>
                            <ActionType>DotNet</ActionType>
                          </Identity>
                          <Disabled>false</Disabled>
                        </FormActionSummary>
                      </Actions>
                    </FormEvent>
                    <FormEvent>
                      <EventType>OnUnrejectDocuments</EventType>
                      <Actions>
                        <FormActionSummary>
                          <Identity>
                            <Id>138B2CDC66174605A44B519FAC61C790</Id>
                            <Name>VerificationControlUnrejectDocumentsAction</Name>
                            <ActionType>DotNet</ActionType>
                          </Identity>
                          <Disabled>false</Disabled>
                        </FormActionSummary>
                      </Actions>
                    </FormEvent>
                    <FormEvent>
                      <EventType>OnRejectPages</EventType>
                      <Actions>
                        <FormActionSummary>
                          <Identity>
                            <Id>FE9DA895D1B0463599239C57E02FBF7C</Id>
                            <Name>VerificationControlRejectPagesAction</Name>
                            <ActionType>DotNet</ActionType>
                          </Identity>
                          <Disabled>false</Disabled>
                        </FormActionSummary>
                      </Actions>
                    </FormEvent>
                    <FormEvent>
                      <EventType>OnUnrejectPages</EventType>
                      <Actions>
                        <FormActionSummary>
                          <Identity>
                            <Id>10BD62AB2CA1453CB9197F078728345A</Id>
                            <Name>VerificationControlUnrejectPagesAction</Name>
                            <ActionType>DotNet</ActionType>
                          </Identity>
                          <Disabled>false</Disabled>
                        </FormActionSummary>
                      </Actions>
                    </FormEvent>
                  </FormControlEvents>
                  <FormIdentity>
                    <Id>BE9F56EA0F3D47EB8ACE375A258B9C38</Id>
                    <AutomaticallyPopulate>false</AutomaticallyPopulate>
                    <Name>t11_Verification</Name>
                    <Version>0</Version>
                  </FormIdentity>
                  <Id>C7DBA2E6031448F492445F5014CD44F0</Id>
                  <Name>VerificationControl</Name>
                  <Margin>
                    <Top>2</Top>
                    <Left>0</Left>
                    <Right>0</Right>
                    <Bottom>0</Bottom>
                  </Margin>
                  <Width>1300</Width>
                  <MinWidth>0</MinWidth>
                  <PercentageWidth>100</PercentageWidth>
                  <Height>650</Height>
                  <Enabled>true</Enabled>
                  <TabIndex>0</TabIndex>
                  <DisplayIndex>1</DisplayIndex>
                  <State>Optional</State>
                  <Style>Default</Style>
                  <StyleSource>Theme</StyleSource>
                  <IsAutoGenerated>false</IsAutoGenerated>
                  <CannotDelete>false</CannotDelete>
                  <ControlAlignment>None</ControlAlignment>
                  <UsePercentageHeight>false</UsePercentageHeight>
                  <PercentageHeight>5</PercentageHeight>
                  <ControlLayout>1</ControlLayout>
                  <ExpandToFit>true</ExpandToFit>
                  <ShowCompleteActivity>true</ShowCompleteActivity>
                  <TakeNextActivity>false</TakeNextActivity>
                  <AutoCompleteBehaviour>CompleteActivity</AutoCompleteBehaviour>
                  <ToolBarSettings>
                    <MainToolBarCommands>
                      <ToolBarCommand>
                        <Command>0</Command>
                        <Disabled>false</Disabled>
                      </ToolBarCommand>
                      <ToolBarCommand>
                        <Command>1</Command>
                        <Disabled>false</Disabled>
                      </ToolBarCommand>
                      <ToolBarCommand>
                        <Command>2</Command>
                        <Disabled>false</Disabled>
                      </ToolBarCommand>
                      <ToolBarCommand>
                        <Command>3</Command>
                        <Disabled>false</Disabled>
                      </ToolBarCommand>
                      <ToolBarCommand>
                        <Command>4</Command>
                        <Disabled>false</Disabled>
                      </ToolBarCommand>
                      <ToolBarCommand>
                        <Command>5</Command>
                        <Disabled>false</Disabled>
                      </ToolBarCommand>
                      <ToolBarCommand>
                        <Command>6</Command>
                        <Disabled>false</Disabled>
                      </ToolBarCommand>
                      <ToolBarCommand>
                        <Command>7</Command>
                        <Disabled>false</Disabled>
                      </ToolBarCommand>
                      <ToolBarCommand>
                        <Command>8</Command>
                        <Disabled>false</Disabled>
                      </ToolBarCommand>
                      <ToolBarCommand>
                        <Command>9</Command>
                        <Disabled>false</Disabled>
                      </ToolBarCommand>
                      <ToolBarCommand>
                        <Command>10</Command>
                        <Disabled>false</Disabled>
                      </ToolBarCommand>
                      <ToolBarCommand>
                        <Command>11</Command>
                        <Disabled>false</Disabled>
                      </ToolBarCommand>
                      <ToolBarCommand>
                        <Command>12</Command>
                        <Disabled>false</Disabled>
                      </ToolBarCommand>
                      <ToolBarCommand>
                        <Command>13</Command>
                        <Disabled>false</Disabled>
                      </ToolBarCommand>
                      <ToolBarCommand>
                        <Command>14</Command>
                        <Disabled>false</Disabled>
                      </ToolBarCommand>
                      <ToolBarCommand>
                        <Command>15</Command>
                        <Disabled>false</Disabled>
                      </ToolBarCommand>
                      <ToolBarCommand>
                        <Command>21</Command>
                        <Disabled>false</Disabled>
                      </ToolBarCommand>
                      <ToolBarCommand>
                        <Command>22</Command>
                        <Disabled>false</Disabled>
                      </ToolBarCommand>
                      <ToolBarCommand>
                        <Command>31</Command>
                        <Disabled>false</Disabled>
                      </ToolBarCommand>
                      <ToolBarCommand>
                        <Command>32</Command>
                        <Disabled>false</Disabled>
                      </ToolBarCommand>
                    </MainToolBarCommands>
                    <ImageViewerToolBarCommands>
                      <ToolBarCommand>
                        <Command>0</Command>
                        <Disabled>false</Disabled>
                      </ToolBarCommand>
                      <ToolBarCommand>
                        <Command>1</Command>
                        <Disabled>false</Disabled>
                      </ToolBarCommand>
                      <ToolBarCommand>
                        <Command>5</Command>
                        <Disabled>false</Disabled>
                      </ToolBarCommand>
                      <ToolBarCommand>
                        <Command>6</Command>
                        <Disabled>false</Disabled>
                      </ToolBarCommand>
                      <ToolBarCommand>
                        <Command>7</Command>
                        <Disabled>false</Disabled>
                      </ToolBarCommand>
                      <ToolBarCommand>
                        <Command>8</Command>
                        <Disabled>false</Disabled>
                      </ToolBarCommand>
                      <ToolBarCommand>
                        <Command>9</Command>
                        <Disabled>false</Disabled>
                      </ToolBarCommand>
                      <ToolBarCommand>
                        <Command>10</Command>
                        <Disabled>false</Disabled>
                      </ToolBarCommand>
                      <ToolBarCommand>
                        <Command>11</Command>
                        <Disabled>false</Disabled>
                      </ToolBarCommand>
                      <ToolBarCommand>
                        <Command>12</Command>
                        <Disabled>false</Disabled>
                      </ToolBarCommand>
                      <ToolBarCommand>
                        <Command>13</Command>
                        <Disabled>false</Disabled>
                      </ToolBarCommand>
                      <ToolBarCommand>
                        <Command>14</Command>
                        <Disabled>false</Disabled>
                      </ToolBarCommand>
                      <ToolBarCommand>
                        <Command>15</Command>
                        <Disabled>false</Disabled>
                      </ToolBarCommand>
                      <ToolBarCommand>
                        <Command>16</Command>
                        <Disabled>false</Disabled>
                      </ToolBarCommand>
                      <ToolBarCommand>
                        <Command>17</Command>
                        <Disabled>false</Disabled>
                      </ToolBarCommand>
                      <ToolBarCommand>
                        <Command>18</Command>
                        <Disabled>false</Disabled>
                      </ToolBarCommand>
                      <ToolBarCommand>
                        <Command>19</Command>
                        <Disabled>false</Disabled>
                      </ToolBarCommand>
                      <ToolBarCommand>
                        <Command>20</Command>
                        <Disabled>false</Disabled>
                      </ToolBarCommand>
                    </ImageViewerToolBarCommands>
                  </ToolBarSettings>
                  <LockedLayout>false</LockedLayout>
                  <DisableAutomaticFieldNavigation>false</DisableAutomaticFieldNavigation>
                  <CompleteActivityWithInvalidFields>false</CompleteActivityWithInvalidFields>
                  <RejectionReasons />
                  <VariablesView>
                    <Columns>
                      <FormColumn>
                        <DisplayIndex>0</DisplayIndex>
                        <Width>1300</Width>
                        <PercentageWidth>0</PercentageWidth>
                        <Height>420</Height>
                        <Rows>
                          <Row>
                            <Width>1300</Width>
                            <Height>20</Height>
                            <DisplayIndex>0</DisplayIndex>
                            <Cells>
                              <Cell>
                                <Id>475821C61F984421B0CC0C8724303B7F</Id>
                                <Name>Cell2</Name>
                                <Collapsible>false</Collapsible>
                                <Collapsed>false</Collapsed>
                                <Visible>true</Visible>
                                <DisplayIndex>0</DisplayIndex>
                                <Width>1300</Width>
                                <PercentageWidth>100</PercentageWidth>
                                <CellLayout>1</CellLayout>
                                <Height>20</Height>
                                <MinHeight>25</MinHeight>
                                <Orientation>1</Orientation>
                                <Border>0</Border>
                                <BackgroundColor>Transparent</BackgroundColor>
                                <CellControls />
                                <TextAlignment>Left</TextAlignment>
                                <Font>
                                  <Bold>false</Bold>
                                  <Italic>false</Italic>
                                  <Overline>false</Overline>
                                  <Size>0</Size>
                                  <Strikeout>false</Strikeout>
                                  <Underline>false</Underline>
                                </Font>
                                <StyleSource>Theme</StyleSource>
                                <CellStyleSource>Theme</CellStyleSource>
                                <Alignment>None</Alignment>
                              </Cell>
                            </Cells>
                          </Row>
                        </Rows>
                        <BackgroundColor>Transparent</BackgroundColor>
                      </FormColumn>
                    </Columns>
                    <Actions />
                  </VariablesView>
                  <DocumentDisplayText>Document</DocumentDisplayText>
                  <FolderDisplayText>Folder</FolderDisplayText>
                  <ActivityDisplayText>Activity</ActivityDisplayText>
                  <ThumbnailPanelDisplayMode>None</ThumbnailPanelDisplayMode>
                </FormControl>
              </CellControls>
              <TextAlignment>Left</TextAlignment>
              <Font>
                <Bold>false</Bold>
                <Italic>false</Italic>
                <Overline>false</Overline>
                <Size>0</Size>
                <Strikeout>false</Strikeout>
                <Underline>false</Underline>
              </Font>
              <StyleSource>Theme</StyleSource>
              <CellStyleSource>Theme</CellStyleSource>
              <Alignment>None</Alignment>
            </Cell>
          </Cells>
        </Row>
      </Rows>
      <BackgroundColor>#FFFFFFFF</BackgroundColor>
    </FormColumn>
  </Columns>
  <InitializationVars />
  <Actions>
    <FormAction xsi:type="DotNetAction">
      <FormIdentity>
        <Id>BE9F56EA0F3D47EB8ACE375A258B9C38</Id>
        <AutomaticallyPopulate>false</AutomaticallyPopulate>
        <Name>t11_Verification</Name>
        <Version>0</Version>
      </FormIdentity>
      <Identity>
        <Id>9499B9CD17434A128AFDE5B912409AA5</Id>
        <Name>VerificationControlLoadBatchAction</Name>
        <ActionType>DotNet</ActionType>
      </Identity>
      <Method>
        <Name>LoadBatch3</Name>
        <ClassName>TotalAgility.Sdk.CaptureRuntimeService</ClassName>
        <AssemblyName>TotalAgility.Sdk, Version=1.0.0.0, Culture=neutral, PublicKeyToken=d86c87abe4a71948</AssemblyName>
        <AssemblyLoadType>Gac</AssemblyLoadType>
        <Parameters>
          <Parameter direction="in" source="session" field="SESSION_ID" datatype="System.String" value="" name="sessionId" selection="false" />
          <Parameter direction="in" source="inline" field="" datatype="System.Int16" value="3" name="activityType" selection="false" />
          <Parameter direction="in" source="" field="" datatype="Agility.Sdk.Model.Activities.JobActivityIdentity" value="" name="jobActivityIdentity" selection="false">
            <member name="NodeId" source="formvariable" type="System.Int16" value="" field="sppNODE_ID" selection="false" index="0" />
            <member name="EmbeddedProcessCount" source="formvariable" type="System.Int16" value="" field="sppEPC" selection="false" index="0" />
            <member name="JobId" source="formvariable" type="System.String" value="" field="sppJOB_ID" selection="false" index="0" />
            <member name="ActivityName" source="formvariable" type="System.String" value="" field="sppACTIVITY_NAME" selection="false" index="0" />
          </Parameter>
          <Parameter direction="in" source="" field="" datatype="Agility.Sdk.Model.Processes.ProcessIdentity" value="" name="processIdentity" selection="false">
            <member name="Id" source="inline" type="System.String" value="" field="" selection="false" index="0" />
            <member name="Version" source="inline" type="System.Double" value="0.0" field="" selection="false" index="0" />
            <member name="Name" source="inline" type="System.String" value="" field="" selection="false" index="0" />
          </Parameter>
          <Parameter direction="in" source="" field="" datatype="Agility.Sdk.Model.Capture.BatchSettings" value="" name="batchSettings" selection="false">
            <member name="AvailableVolume" source="" type="System.String" field="" selection="false" index="0" />
            <member name="DocumentVariant" source="form" type="System.String" value="" field="VerificationControl.DocumentVariantName" selection="false" index="0" />
            <member name="ActivityVariant" source="form" type="System.String" value="" field="VerificationControl.ActivityVariantName" selection="false" index="0" />
          </Parameter>
          <Parameter direction="ret" source="form" field="VerificationControl.taData.initializationData" datatype="Agility.Sdk.Model.Capture.ScanCNJInitializationData" name="ReturnParameter" selection="false" />
        </Parameters>
        <AssemblyFilePath>TotalAgility.Sdk, Version=1.0.0.0, Culture=neutral, PublicKeyToken=d86c87abe4a71948</AssemblyFilePath>
        <DupMethodNo>1</DupMethodNo>
        <DupMethodNoSpecified>true</DupMethodNoSpecified>
      </Method>
      <Languages>
        <EventLanguage>
          <Id>Default</Id>
          <Language>Default</Language>
        </EventLanguage>
      </Languages>
      <Controls />
      <FiringCondition />
      <SingleActionBatch>false</SingleActionBatch>
      <IsReadOnly>true</IsReadOnly>
      <IsCapture>true</IsCapture>
      <ReturnOutputsWithoutProcessing>true</ReturnOutputsWithoutProcessing>
      <ExcludeFromVariablesDeployedForm>true</ExcludeFromVariablesDeployedForm>
    </FormAction>
    <FormAction xsi:type="DotNetAction">
      <FormIdentity>
        <Id>BE9F56EA0F3D47EB8ACE375A258B9C38</Id>
        <AutomaticallyPopulate>false</AutomaticallyPopulate>
        <Name>t11_Verification</Name>
        <Version>0</Version>
      </FormIdentity>
      <Identity>
        <Id>4B51110B90AD4B54B557342DCF2ED50E</Id>
        <Name>VerificationControlUnloadBatchCompleteAction</Name>
        <ActionType>DotNet</ActionType>
      </Identity>
      <Method>
        <Name>UnloadBatch</Name>
        <ClassName>TotalAgility.Sdk.CaptureRuntimeService</ClassName>
        <AssemblyName>TotalAgility.Sdk, Version=1.0.0.0, Culture=neutral, PublicKeyToken=d86c87abe4a71948</AssemblyName>
        <AssemblyLoadType>Gac</AssemblyLoadType>
        <Parameters>
          <Parameter direction="in" source="session" field="SESSION_ID" datatype="System.String" value="" name="sessionId" selection="false" />
          <Parameter direction="in" source="formvariable" field="BatchId" datatype="System.String" value="" name="batchId" selection="false" />
          <Parameter direction="in" source="form" field="VerificationControl.jsonData" datatype="System.String" value="" name="jsonData" selection="false" />
          <Parameter direction="in" source="inline" field="" datatype="System.Int16" value="0" name="sessionState" selection="false" />
        </Parameters>
        <AssemblyFilePath>TotalAgility.Sdk, Version=1.0.0.0, Culture=neutral, PublicKeyToken=d86c87abe4a71948</AssemblyFilePath>
        <DupMethodNo>1</DupMethodNo>
        <DupMethodNoSpecified>true</DupMethodNoSpecified>
      </Method>
      <Languages>
        <EventLanguage>
          <Id>Default</Id>
          <Language>Default</Language>
        </EventLanguage>
      </Languages>
      <Controls />
      <FiringCondition />
      <SingleActionBatch>false</SingleActionBatch>
      <IsReadOnly>true</IsReadOnly>
      <IsCapture>true</IsCapture>
      <ReturnOutputsWithoutProcessing>false</ReturnOutputsWithoutProcessing>
      <ExcludeFromVariablesDeployedForm>true</ExcludeFromVariablesDeployedForm>
    </FormAction>
    <FormAction xsi:type="DotNetAction">
      <FormIdentity>
        <Id>BE9F56EA0F3D47EB8ACE375A258B9C38</Id>
        <AutomaticallyPopulate>false</AutomaticallyPopulate>
        <Name>t11_Verification</Name>
        <Version>0</Version>
      </FormIdentity>
      <Identity>
        <Id>E3D7BC472766474A9A9278882002D71E</Id>
        <Name>VerificationControlUnloadBatchCancelAction</Name>
        <ActionType>DotNet</ActionType>
      </Identity>
      <Method>
        <Name>CancelBatch</Name>
        <ClassName>TotalAgility.Sdk.CaptureRuntimeService</ClassName>
        <AssemblyName>TotalAgility.Sdk, Version=1.0.0.0, Culture=neutral, PublicKeyToken=d86c87abe4a71948</AssemblyName>
        <AssemblyLoadType>Gac</AssemblyLoadType>
        <Parameters>
          <Parameter direction="in" source="session" field="SESSION_ID" datatype="System.String" value="" name="sessionId" selection="false" />
          <Parameter direction="in" source="formvariable" field="BatchId" datatype="System.String" value="" name="batchId" selection="false" />
          <Parameter direction="in" source="form" field="VerificationControl.jsonData" datatype="System.String" value="" name="jsonData" selection="false" />
          <Parameter direction="in" source="inline" field="" datatype="System.Int16" value="1" name="sessionState" selection="false" />
        </Parameters>
        <AssemblyFilePath>TotalAgility.Sdk, Version=1.0.0.0, Culture=neutral, PublicKeyToken=d86c87abe4a71948</AssemblyFilePath>
        <DupMethodNo>1</DupMethodNo>
        <DupMethodNoSpecified>true</DupMethodNoSpecified>
      </Method>
      <Languages>
        <EventLanguage>
          <Id>Default</Id>
          <Language>Default</Language>
        </EventLanguage>
      </Languages>
      <Controls />
      <FiringCondition />
      <SingleActionBatch>false</SingleActionBatch>
      <IsReadOnly>true</IsReadOnly>
      <IsCapture>true</IsCapture>
      <ReturnOutputsWithoutProcessing>true</ReturnOutputsWithoutProcessing>
      <ExcludeFromVariablesDeployedForm>true</ExcludeFromVariablesDeployedForm>
    </FormAction>
    <FormAction xsi:type="DotNetAction">
      <FormIdentity>
        <Id>BE9F56EA0F3D47EB8ACE375A258B9C38</Id>
        <AutomaticallyPopulate>false</AutomaticallyPopulate>
        <Name>t11_Verification</Name>
        <Version>0</Version>
      </FormIdentity>
      <Identity>
        <Id>F86DFE516EBB456DA1F46A438758485D</Id>
        <Name>VerificationControlSaveChanges</Name>
        <ActionType>DotNet</ActionType>
      </Identity>
      <Method>
        <Name>SaveChanges2</Name>
        <ClassName>TotalAgility.Sdk.CaptureRuntimeService</ClassName>
        <AssemblyName>TotalAgility.Sdk.dll</AssemblyName>
        <AssemblyLoadType>File</AssemblyLoadType>
        <Parameters>
          <Parameter direction="in" source="session" field="SESSION_ID" datatype="System.String" value="" name="sessionId" selection="false" />
          <Parameter direction="in" source="" field="" datatype="Agility.Sdk.Model.Capture.CommonInfo" value="" name="commonInfo" selection="false">
            <member name="BatchId" source="formvariable" type="System.String" value="" field="BatchId" selection="false" index="0" />
            <member name="ActivityType" source="inline" type="System.Int16" value="3" field="" selection="false" index="0" />
            <member name="CancelingActivity" source="form" type="System.Boolean" value="" field="VerificationControl.cancelingActivity" selection="false" index="0" />
          </Parameter>
          <Parameter direction="in" source="form" field="VerificationControl.batchEditOperation.changes" datatype="System.Object" value="" name="changes" selection="false" />
          <Parameter direction="ret" source="inlinescript" field="INLINESCRIPT" datatype="Kofax.CEBPM.ThinClient.DocumentServices.ValidationDataContainer" value="" name="Return Parameter" selection="false" />
        </Parameters>
        <AssemblyFilePath>TotalAgility.Sdk.dll</AssemblyFilePath>
        <DupMethodNo>1</DupMethodNo>
        <DupMethodNoSpecified>true</DupMethodNoSpecified>
      </Method>
      <Languages>
        <EventLanguage>
          <Id>Default</Id>
          <Language>Default</Language>
        </EventLanguage>
      </Languages>
      <Controls />
      <FiringCondition />
      <SingleActionBatch>false</SingleActionBatch>
      <IsReadOnly>true</IsReadOnly>
      <IsCapture>true</IsCapture>
      <ReturnOutputsWithoutProcessing>true</ReturnOutputsWithoutProcessing>
      <ExcludeFromVariablesDeployedForm>true</ExcludeFromVariablesDeployedForm>
    </FormAction>
    <FormAction xsi:type="DotNetAction">
      <FormIdentity>
        <Id>BE9F56EA0F3D47EB8ACE375A258B9C38</Id>
        <AutomaticallyPopulate>false</AutomaticallyPopulate>
        <Name>t11_Verification</Name>
        <Version>0</Version>
      </FormIdentity>
      <Identity>
        <Id>D17E1B4E93A8430788EEA70C629FB0DD</Id>
        <Name>takependingactivity</Name>
        <ActionType>DotNet</ActionType>
      </Identity>
      <Method>
        <Name>TakeActivity</Name>
        <ClassName>TotalAgility.Sdk.ActivityService</ClassName>
        <AssemblyName>TotalAgility.Sdk.dll</AssemblyName>
        <AssemblyLoadType>File</AssemblyLoadType>
        <Parameters>
          <Parameter direction="in" source="session" field="SESSION_ID" datatype="System.String" value="" name="sessionId" selection="false" />
          <Parameter direction="in" source="" field="" datatype="Agility.Sdk.Model.Activities.JobActivityIdentity" value="" name="jobActivityIdentity" selection="false">
            <member name="NodeId" source="formvariable" type="System.Int16" value="" field="sppNODE_ID" selection="false" index="0" />
            <member name="EmbeddedProcessCount" source="formvariable" type="System.Int16" value="" field="sppEPC" selection="false" index="0" />
            <member name="JobId" source="formvariable" type="System.String" value="" field="sppJOB_ID" selection="false" index="0" />
            <member name="ActivityName" source="formvariable" type="System.String" value="" field="sppACTIVITY_NAME" selection="false" index="0" />
          </Parameter>
          <Parameter direction="ret" source="" field="" datatype="Agility.Sdk.Model.Activities.JobActivity" value="" prelimdatatype="" subfieldsource="" subfield="" name="Return Parameter" selection="false">
            <member name="Identity" type="Agility.Sdk.Model.Activities.JobActivityIdentity" selection="false" index="0">
              <member name="NodeId" source="formvariable" type="System.Int16" value="" field="sppNODE_ID" selection="false" index="0" />
              <member name="EmbeddedProcessCount" source="formvariable" type="System.Int16" value="" field="sppEPC" selection="false" index="0" />
              <member name="JobId" source="formvariable" type="System.String" value="" field="sppJOB_ID" selection="false" index="0" />
              <member name="ActivityName" source="formvariable" type="System.String" value="" field="sppACTIVITY_NAME" selection="false" index="0" />
            </member>
            <member name="InputOutputVariables" source="" type="Agility.Sdk.Model.Variables.InputOutputVariables" value="" field="" selection="false" index="0">
              <member name="InputVariables" source="" type="Agility.Sdk.Model.Variables.JobVariable[]" value="" field="" selection="false" index="0">
                <member name="" type="Agility.Sdk.Model.Variables.JobVariable" selection="false" index="0">
                  <member name="Id" source="inline" type="System.String" value="FOLDER" field="" selection="false" index="0" />
                  <member name="VariableType" type="Agility.Sdk.Model.Variables.VariableType" selection="false" index="0">
                    <member name="Value" source="inline" type="System.Int16" value="Folder" field="" selection="false" index="0" />
                    <member name="FormattedAsText" source="inline" type="System.String" value="" field="" selection="false" index="0" />
                  </member>
                  <member name="DisplayName" source="inline" type="System.String" field="" selection="false" index="0" />
                </member>
              </member>
              <member name="OutputVariables" source="" type="Agility.Sdk.Model.Variables.JobVariable[]" value="" field="" selection="false" index="0" />
            </member>
            <member name="ThreadpoolId" source="" type="System.Int16" value="" field="" selection="false" index="0" />
            <member name="SettingsXml" source="" type="System.String" value="" field="" selection="false" index="0" />
            <member name="HelpText" source="" type="System.String" value="" field="" selection="false" index="0" />
            <member name="Priority" source="" type="System.Int16" value="" field="" selection="false" index="0" />
            <member name="DueDate" source="" type="System.DateTime" value="" field="" selection="false" index="0" />
            <member name="Process" type="Agility.Sdk.Model.Processes.ProcessIdentity" selection="false" index="0">
              <member name="Id" source="" type="System.String" value="" field="" selection="false" index="0" />
              <member name="Version" source="" type="System.Double" value="" field="" selection="false" index="0" />
              <member name="Name" source="" type="System.String" value="" field="" selection="false" index="0" />
            </member>
            <member name="ActivityType" type="Agility.Sdk.Model.Activities.ActivityType" selection="false" index="0">
              <member name="Value" source="" type="System.Int16" value="" field="" selection="false" index="0" />
            </member>
            <member name="AssociatedFile" source="" type="System.String" value="" field="" selection="false" index="0" />
            <member name="CustomData" source="" type="System.String" value="" field="" selection="false" index="0" />
          </Parameter>
        </Parameters>
        <AssemblyFilePath>TotalAgility.Sdk.dll</AssemblyFilePath>
        <DupMethodNo>1</DupMethodNo>
        <DupMethodNoSpecified>true</DupMethodNoSpecified>
      </Method>
      <Languages>
        <EventLanguage>
          <Id>Default</Id>
          <Language>Default</Language>
        </EventLanguage>
      </Languages>
      <Controls />
      <FiringCondition />
      <SingleActionBatch>false</SingleActionBatch>
      <IsReadOnly>false</IsReadOnly>
      <IsCapture>false</IsCapture>
      <ReturnOutputsWithoutProcessing>false</ReturnOutputsWithoutProcessing>
      <ExcludeFromVariablesDeployedForm>false</ExcludeFromVariablesDeployedForm>
    </FormAction>
    <FormAction xsi:type="DotNetAction">
      <FormIdentity>
        <Id>BE9F56EA0F3D47EB8ACE375A258B9C38</Id>
        <AutomaticallyPopulate>false</AutomaticallyPopulate>
        <Name>t11_Verification</Name>
        <Version>0</Version>
      </FormIdentity>
      <Identity>
        <Id>AE48645C345C49B384BAE0BC406674B4</Id>
        <Name>activitycomplete</Name>
        <ActionType>DotNet</ActionType>
      </Identity>
      <Method>
        <Name>CompleteActivity</Name>
        <ClassName>TotalAgility.Sdk.ActivityService</ClassName>
        <AssemblyName>TotalAgility.Sdk.dll</AssemblyName>
        <AssemblyLoadType>File</AssemblyLoadType>
        <Parameters>
          <Parameter direction="in" source="session" field="SESSION_ID" datatype="System.String" value="" name="sessionId" selection="false" />
          <Parameter direction="in" source="" field="" datatype="Agility.Sdk.Model.Activities.JobActivityIdentity" value="" name="jobActivityIdentity" selection="false">
            <member name="NodeId" source="formvariable" type="System.Int16" value="" field="sppNODE_ID" selection="false" index="0" />
            <member name="EmbeddedProcessCount" source="formvariable" type="System.Int16" value="" field="sppEPC" selection="false" index="0" />
            <member name="JobId" source="formvariable" type="System.String" value="" field="sppJOB_ID" selection="false" index="0" />
            <member name="ActivityName" source="formvariable" type="System.String" value="" field="sppACTIVITY_NAME" selection="false" index="0" />
          </Parameter>
          <Parameter direction="in" source="" field="" datatype="Agility.Sdk.Model.Activities.JobActivityOutput" value="" name="jobActivityOutput" selection="false" />
        </Parameters>
        <AssemblyFilePath>TotalAgility.Sdk.dll</AssemblyFilePath>
        <DupMethodNo>1</DupMethodNo>
        <DupMethodNoSpecified>true</DupMethodNoSpecified>
      </Method>
      <Languages>
        <EventLanguage>
          <Id>Default</Id>
          <Language>Default</Language>
        </EventLanguage>
      </Languages>
      <Controls />
      <FiringCondition />
      <SingleActionBatch>false</SingleActionBatch>
      <IsReadOnly>false</IsReadOnly>
      <IsCapture>false</IsCapture>
      <ReturnOutputsWithoutProcessing>false</ReturnOutputsWithoutProcessing>
      <ExcludeFromVariablesDeployedForm>true</ExcludeFromVariablesDeployedForm>
    </FormAction>
    <FormAction xsi:type="DotNetAction">
      <FormIdentity>
        <Id>BE9F56EA0F3D47EB8ACE375A258B9C38</Id>
        <AutomaticallyPopulate>false</AutomaticallyPopulate>
        <Name>t11_Verification</Name>
        <Version>0</Version>
      </FormIdentity>
      <Identity>
        <Id>0455C0141FE54D119FBF20C7C9837CB0</Id>
        <Name>CompleteActivityAndProgress</Name>
        <ActionType>DotNet</ActionType>
      </Identity>
      <Method>
        <Name>CompleteActivityAndProgress</Name>
        <ClassName>TotalAgility.Sdk.ActivityService</ClassName>
        <AssemblyName>TotalAgility.Sdk.dll</AssemblyName>
        <AssemblyLoadType>File</AssemblyLoadType>
        <Parameters>
          <Parameter direction="in" source="session" field="SESSION_ID" datatype="System.String" value="" name="sessionId" selection="false" />
          <Parameter direction="in" source="" field="" datatype="Agility.Sdk.Model.Activities.JobActivityIdentity" value="" name="jobActivityIdentity" selection="false">
            <member name="NodeId" source="formvariable" type="System.Int16" value="" field="sppNODE_ID" selection="false" index="0" />
            <member name="EmbeddedProcessCount" source="formvariable" type="System.Int16" value="" field="sppEPC" selection="false" index="0" />
            <member name="JobId" source="formvariable" type="System.String" value="" field="sppJOB_ID" selection="false" index="0" />
            <member name="ActivityName" source="formvariable" type="System.String" value="" field="sppACTIVITY_NAME" selection="false" index="0" />
          </Parameter>
          <Parameter direction="in" source="" field="" datatype="Agility.Sdk.Model.Activities.JobActivityOutput" value="" name="jobActivityOutput" selection="false" />
          <Parameter direction="ret" source="" field="" datatype="Agility.Sdk.Model.Jobs.JobProgressOutput" name="Return Parameter" selection="false" />
        </Parameters>
        <AssemblyFilePath>TotalAgility.Sdk.dll</AssemblyFilePath>
        <DupMethodNo>1</DupMethodNo>
        <DupMethodNoSpecified>true</DupMethodNoSpecified>
      </Method>
      <Languages>
        <EventLanguage>
          <Id>Default</Id>
          <Language>Default</Language>
        </EventLanguage>
      </Languages>
      <Controls />
      <FiringCondition />
      <SingleActionBatch>false</SingleActionBatch>
      <IsReadOnly>false</IsReadOnly>
      <IsCapture>false</IsCapture>
      <ReturnOutputsWithoutProcessing>false</ReturnOutputsWithoutProcessing>
      <ExcludeFromVariablesDeployedForm>true</ExcludeFromVariablesDeployedForm>
    </FormAction>
    <FormAction xsi:type="DotNetAction">
      <FormIdentity>
        <Id>BE9F56EA0F3D47EB8ACE375A258B9C38</Id>
        <AutomaticallyPopulate>false</AutomaticallyPopulate>
        <Name>t11_Verification</Name>
        <Version>0</Version>
      </FormIdentity>
      <Identity>
        <Id>50F0645B4B7245628A8E751D3410DF57</Id>
        <Name>cancelactivity</Name>
        <ActionType>DotNet</ActionType>
      </Identity>
      <Method>
        <Name>CancelActivity</Name>
        <ClassName>TotalAgility.Sdk.ActivityService</ClassName>
        <AssemblyName>TotalAgility.Sdk.dll</AssemblyName>
        <AssemblyLoadType>File</AssemblyLoadType>
        <Parameters>
          <Parameter direction="in" source="session" field="SESSION_ID" datatype="System.String" value="" name="sessionId" selection="false" />
          <Parameter direction="in" source="" field="" datatype="Agility.Sdk.Model.Activities.JobActivityIdentity" value="" name="jobActivityIdentity" selection="false">
            <member name="NodeId" source="formvariable" type="System.Int16" value="" field="sppNODE_ID" selection="false" index="0" />
            <member name="EmbeddedProcessCount" source="formvariable" type="System.Int16" value="" field="sppEPC" selection="false" index="0" />
            <member name="JobId" source="formvariable" type="System.String" value="" field="sppJOB_ID" selection="false" index="0" />
            <member name="ActivityName" source="formvariable" type="System.String" value="" field="sppACTIVITY_NAME" selection="false" index="0" />
          </Parameter>
        </Parameters>
        <AssemblyFilePath>TotalAgility.Sdk.dll</AssemblyFilePath>
        <DupMethodNo>1</DupMethodNo>
        <DupMethodNoSpecified>true</DupMethodNoSpecified>
      </Method>
      <Languages>
        <EventLanguage>
          <Id>Default</Id>
          <Language>Default</Language>
        </EventLanguage>
      </Languages>
      <Controls />
      <FiringCondition />
      <SingleActionBatch>false</SingleActionBatch>
      <IsReadOnly>false</IsReadOnly>
      <IsCapture>false</IsCapture>
      <ReturnOutputsWithoutProcessing>false</ReturnOutputsWithoutProcessing>
      <ExcludeFromVariablesDeployedForm>true</ExcludeFromVariablesDeployedForm>
    </FormAction>
    <FormAction xsi:type="RedirectAction">
      <FormIdentity>
        <Id>BE9F56EA0F3D47EB8ACE375A258B9C38</Id>
        <AutomaticallyPopulate>false</AutomaticallyPopulate>
        <Name>t11_Verification</Name>
        <Version>0</Version>
      </FormIdentity>
      <Identity>
        <Id>38E67CF21C614D6CB82A2DA37F12C62B</Id>
        <Name>redirCancel</Name>
        <ActionType>Redirect</ActionType>
      </Identity>
      <Method>
        <Parameters />
        <DupMethodNoSpecified>false</DupMethodNoSpecified>
      </Method>
      <Languages>
        <EventLanguage>
          <Id>Default</Id>
          <Language>Default</Language>
        </EventLanguage>
      </Languages>
      <Controls />
      <FiringCondition />
      <SingleActionBatch>false</SingleActionBatch>
      <IsReadOnly>false</IsReadOnly>
      <IsCapture>false</IsCapture>
      <ReturnOutputsWithoutProcessing>false</ReturnOutputsWithoutProcessing>
      <ExcludeFromVariablesDeployedForm>true</ExcludeFromVariablesDeployedForm>
      <Redirect>
        <IsModalWindow>false</IsModalWindow>
        <Page>WORKQUEUE_FORM</Page>
        <Target>SameWindow</Target>
        <RedirectType>Dynamic</RedirectType>
        <PopupWidth>0</PopupWidth>
        <PopupHeight>0</PopupHeight>
        <IgnoreRedirectConfirmation>true</IgnoreRedirectConfirmation>
        <UseBreadcrumbTrail>false</UseBreadcrumbTrail>
      </Redirect>
    </FormAction>
    <FormAction xsi:type="SamePageAction">
      <FormIdentity>
        <Id>BE9F56EA0F3D47EB8ACE375A258B9C38</Id>
        <AutomaticallyPopulate>false</AutomaticallyPopulate>
        <Name>t11_Verification</Name>
        <Version>0</Version>
      </FormIdentity>
      <Identity>
        <Id>8B39D9612F124A16B0E636BEF1C77FF7</Id>
        <Name>SamePageEvent1</Name>
        <ActionType>SamePage</ActionType>
      </Identity>
      <Method>
        <Parameters>
          <Parameter direction="in" source="Session" field="WORKQUEUE_FORM" value="value" subfieldsource="Inline" subfield="" selection="false" />
        </Parameters>
        <DupMethodNoSpecified>false</DupMethodNoSpecified>
      </Method>
      <Languages>
        <EventLanguage>
          <Id>Default</Id>
          <Language>Default</Language>
        </EventLanguage>
      </Languages>
      <Controls />
      <FiringCondition />
      <SingleActionBatch>false</SingleActionBatch>
      <IsReadOnly>false</IsReadOnly>
      <IsCapture>false</IsCapture>
      <ReturnOutputsWithoutProcessing>false</ReturnOutputsWithoutProcessing>
      <ExcludeFromVariablesDeployedForm>true</ExcludeFromVariablesDeployedForm>
    </FormAction>
    <FormAction xsi:type="RedirectAction">
      <FormIdentity>
        <Id>BE9F56EA0F3D47EB8ACE375A258B9C38</Id>
        <AutomaticallyPopulate>false</AutomaticallyPopulate>
        <Name>t11_Verification</Name>
        <Version>0</Version>
      </FormIdentity>
      <Identity>
        <Id>406CB4C8F41C447487211A0536879E25</Id>
        <Name>redirNextActivity</Name>
        <ActionType>Redirect</ActionType>
      </Identity>
      <Method>
        <Parameters />
        <DupMethodNoSpecified>false</DupMethodNoSpecified>
      </Method>
      <Languages>
        <EventLanguage>
          <Id>Default</Id>
          <Language>Default</Language>
        </EventLanguage>
      </Languages>
      <Controls />
      <FiringCondition />
      <SingleActionBatch>false</SingleActionBatch>
      <IsReadOnly>false</IsReadOnly>
      <IsCapture>false</IsCapture>
      <ReturnOutputsWithoutProcessing>false</ReturnOutputsWithoutProcessing>
      <ExcludeFromVariablesDeployedForm>true</ExcludeFromVariablesDeployedForm>
      <Redirect>
        <IsModalWindow>false</IsModalWindow>
        <Page>AssociatedFile?JOB_ID=sppJOB_ID&amp;EPC=sppEPC&amp;NODE_ID=sppNODE_ID</Page>
        <Target>SameWindow</Target>
        <RedirectType>Dynamic</RedirectType>
        <PopupWidth>0</PopupWidth>
        <PopupHeight>0</PopupHeight>
        <IgnoreRedirectConfirmation>true</IgnoreRedirectConfirmation>
        <UseBreadcrumbTrail>false</UseBreadcrumbTrail>
      </Redirect>
    </FormAction>
    <FormAction xsi:type="DotNetAction">
      <FormIdentity>
        <Id>BE9F56EA0F3D47EB8ACE375A258B9C38</Id>
        <AutomaticallyPopulate>false</AutomaticallyPopulate>
        <Name>t11_Verification</Name>
        <Version>0</Version>
      </FormIdentity>
      <Identity>
        <Id>6D4E0D544AE644F7ADFCC0AAFCC017DD</Id>
        <Name>TakeNextActivity</Name>
        <ActionType>DotNet</ActionType>
      </Identity>
      <Method>
        <Name>TakeNextActivity2</Name>
        <ClassName>TotalAgility.Sdk.ActivityService</ClassName>
        <AssemblyName>TotalAgility.Sdk.dll</AssemblyName>
        <AssemblyLoadType>File</AssemblyLoadType>
        <Parameters>
          <Parameter direction="in" source="session" field="SESSION_ID" datatype="System.String" value="" name="sessionId" selection="false" />
          <Parameter direction="in" source="" field="" datatype="Agility.Sdk.Model.Activities.TakeNextActivityFilter" value="" name="filter" selection="false">
            <member name="UseCombinedWorkQueue" source="inline" type="System.Boolean" value="true" field="" selection="false" index="0" />
            <member name="UseWorkAllocationRules" source="inline" type="System.Boolean" value="true" field="" selection="false" index="0" />
            <member name="UserFilterData" source="session" type="System.String" value="" field="" selection="false" index="0" />
          </Parameter>
          <Parameter direction="ret" source="" field="" datatype="Agility.Sdk.Model.Activities.NextActivity" value="" name="Return Parameter" selection="false">
            <member name="FoundActivity" source="formvariable" type="System.Boolean" value="" field="FoundActivity" selection="false" index="0" />
            <member name="JobId" source="formvariable" type="System.String" value="" field="sppJOB_ID" selection="false" index="0" />
            <member name="EmbeddedProcessCount" source="formvariable" type="System.Int16" value="" field="sppEPC" selection="false" index="0" />
            <member name="NodeId" source="formvariable" type="System.Int32" value="" field="sppNODE_ID" selection="false" index="0" />
            <member name="AssociatedFile" source="formvariable" type="System.String" value="" field="AssociatedFile" selection="false" index="0" />
          </Parameter>
        </Parameters>
        <AssemblyFilePath>TotalAgility.Sdk.dll</AssemblyFilePath>
        <DupMethodNo>1</DupMethodNo>
        <DupMethodNoSpecified>true</DupMethodNoSpecified>
      </Method>
      <Languages>
        <EventLanguage>
          <Id>Default</Id>
          <Language>Default</Language>
        </EventLanguage>
      </Languages>
      <Controls />
      <FiringCondition />
      <SingleActionBatch>false</SingleActionBatch>
      <IsReadOnly>false</IsReadOnly>
      <IsCapture>false</IsCapture>
      <ReturnOutputsWithoutProcessing>false</ReturnOutputsWithoutProcessing>
      <ExcludeFromVariablesDeployedForm>true</ExcludeFromVariablesDeployedForm>
    </FormAction>
    <FormAction xsi:type="BeginConditionAction">
      <FormIdentity>
        <Id>BE9F56EA0F3D47EB8ACE375A258B9C38</Id>
        <AutomaticallyPopulate>false</AutomaticallyPopulate>
        <Name>t11_Verification</Name>
        <Version>0</Version>
      </FormIdentity>
      <Identity>
        <Id>F436586C01A54915B595EB26037CE7E2</Id>
        <Name>beginFoundNextAction</Name>
        <ActionType>BeginCondition</ActionType>
      </Identity>
      <Method>
        <Parameters />
        <DupMethodNoSpecified>false</DupMethodNoSpecified>
      </Method>
      <Languages>
        <EventLanguage>
          <Id>Default</Id>
          <Language>Default</Language>
        </EventLanguage>
      </Languages>
      <Controls />
      <FiringCondition>
        <Condition>
          <Id>FoundActivity</Id>
          <Operator>EQUALS</Operator>
          <Value>true</Value>
          <Source>Inline</Source>
          <ControlType>FormVariable</ControlType>
          <FieldType>Boolean</FieldType>
        </Condition>
      </FiringCondition>
      <SingleActionBatch>false</SingleActionBatch>
      <IsReadOnly>false</IsReadOnly>
      <IsCapture>false</IsCapture>
      <ReturnOutputsWithoutProcessing>false</ReturnOutputsWithoutProcessing>
      <ExcludeFromVariablesDeployedForm>true</ExcludeFromVariablesDeployedForm>
      <RuleData>
        <RuleInputs>
          <RuleInput>
            <Id>FoundActivity</Id>
            <Scope>FormVariable</Scope>
            <VariableType>Bool</VariableType>
          </RuleInput>
        </RuleInputs>
        <Script>FoundActivity = true</Script>
        <RuleType>BeingConditionAction</RuleType>
      </RuleData>
    </FormAction>
    <FormAction xsi:type="EndConditionAction">
      <FormIdentity>
        <Id>BE9F56EA0F3D47EB8ACE375A258B9C38</Id>
        <AutomaticallyPopulate>false</AutomaticallyPopulate>
        <Name>t11_Verification</Name>
        <Version>0</Version>
      </FormIdentity>
      <Identity>
        <Id>B4A67EF520C14B338BDA3E6CA919C3FE</Id>
        <Name>endFoundNextAction</Name>
        <ActionType>EndCondition</ActionType>
      </Identity>
      <Method>
        <Parameters />
        <DupMethodNoSpecified>false</DupMethodNoSpecified>
      </Method>
      <Languages>
        <EventLanguage>
          <Id>Default</Id>
          <Language>Default</Language>
        </EventLanguage>
      </Languages>
      <Controls />
      <FiringCondition />
      <SingleActionBatch>false</SingleActionBatch>
      <IsReadOnly>false</IsReadOnly>
      <IsCapture>false</IsCapture>
      <ReturnOutputsWithoutProcessing>false</ReturnOutputsWithoutProcessing>
      <ExcludeFromVariablesDeployedForm>true</ExcludeFromVariablesDeployedForm>
    </FormAction>
    <FormAction xsi:type="BeginConditionAction">
      <FormIdentity>
        <Id>BE9F56EA0F3D47EB8ACE375A258B9C38</Id>
        <AutomaticallyPopulate>false</AutomaticallyPopulate>
        <Name>t11_Verification</Name>
        <Version>0</Version>
      </FormIdentity>
      <Identity>
        <Id>FD7D76BA356D4CF0B178062B2759CABB</Id>
        <Name>beginNextActivityNotFound</Name>
        <ActionType>BeginCondition</ActionType>
      </Identity>
      <Method>
        <Parameters />
        <DupMethodNoSpecified>false</DupMethodNoSpecified>
      </Method>
      <Languages>
        <EventLanguage>
          <Id>Default</Id>
          <Language>Default</Language>
        </EventLanguage>
      </Languages>
      <Controls />
      <FiringCondition>
        <Condition>
          <Id>FoundActivity</Id>
          <Operator>EQUALS</Operator>
          <Value>false</Value>
          <Source>Inline</Source>
          <ControlType>FormVariable</ControlType>
          <FieldType>Boolean</FieldType>
        </Condition>
      </FiringCondition>
      <SingleActionBatch>false</SingleActionBatch>
      <IsReadOnly>false</IsReadOnly>
      <IsCapture>false</IsCapture>
      <ReturnOutputsWithoutProcessing>false</ReturnOutputsWithoutProcessing>
      <ExcludeFromVariablesDeployedForm>true</ExcludeFromVariablesDeployedForm>
      <RuleData>
        <RuleInputs>
          <RuleInput>
            <Id>FoundActivity</Id>
            <Scope>FormVariable</Scope>
            <VariableType>Bool</VariableType>
          </RuleInput>
        </RuleInputs>
        <Script>FoundActivity = false</Script>
        <RuleType>BeingConditionAction</RuleType>
      </RuleData>
    </FormAction>
    <FormAction xsi:type="EndConditionAction">
      <FormIdentity>
        <Id>BE9F56EA0F3D47EB8ACE375A258B9C38</Id>
        <AutomaticallyPopulate>false</AutomaticallyPopulate>
        <Name>t11_Verification</Name>
        <Version>0</Version>
      </FormIdentity>
      <Identity>
        <Id>9A476CDFCDCE42A6BB6E3247C19247DC</Id>
        <Name>endNextActivityNotFound</Name>
        <ActionType>EndCondition</ActionType>
      </Identity>
      <Method>
        <Parameters />
        <DupMethodNoSpecified>false</DupMethodNoSpecified>
      </Method>
      <Languages>
        <EventLanguage>
          <Id>Default</Id>
          <Language>Default</Language>
        </EventLanguage>
      </Languages>
      <Controls />
      <FiringCondition />
      <SingleActionBatch>false</SingleActionBatch>
      <IsReadOnly>false</IsReadOnly>
      <IsCapture>false</IsCapture>
      <ReturnOutputsWithoutProcessing>false</ReturnOutputsWithoutProcessing>
      <ExcludeFromVariablesDeployedForm>true</ExcludeFromVariablesDeployedForm>
    </FormAction>
    <FormAction xsi:type="BeginConditionAction">
      <FormIdentity>
        <Id>BE9F56EA0F3D47EB8ACE375A258B9C38</Id>
        <AutomaticallyPopulate>false</AutomaticallyPopulate>
        <Name>t11_Verification</Name>
        <Version>0</Version>
      </FormIdentity>
      <Identity>
        <Id>50EEEDB8F2324AFB84D94488AC1D87EA</Id>
        <Name>beginNextAssociatedFileFound</Name>
        <ActionType>BeginCondition</ActionType>
      </Identity>
      <Method>
        <Parameters />
        <DupMethodNoSpecified>false</DupMethodNoSpecified>
      </Method>
      <Languages>
        <EventLanguage>
          <Id>Default</Id>
          <Language>Default</Language>
        </EventLanguage>
      </Languages>
      <Controls />
      <FiringCondition>
        <Condition>
          <Id>AssociatedFile</Id>
          <Operator>NOT EQUALS</Operator>
          <Value>""</Value>
          <Source>Inline</Source>
          <ControlType>FormVariable</ControlType>
          <FieldType>String</FieldType>
        </Condition>
      </FiringCondition>
      <SingleActionBatch>false</SingleActionBatch>
      <IsReadOnly>false</IsReadOnly>
      <IsCapture>false</IsCapture>
      <ReturnOutputsWithoutProcessing>false</ReturnOutputsWithoutProcessing>
      <ExcludeFromVariablesDeployedForm>true</ExcludeFromVariablesDeployedForm>
      <RuleData>
        <RuleInputs>
          <RuleInput>
            <Id>AssociatedFile</Id>
            <Scope>FormVariable</Scope>
            <VariableType>String</VariableType>
          </RuleInput>
        </RuleInputs>
        <Script>AssociatedFile != ""</Script>
        <RuleType>BeingConditionAction</RuleType>
      </RuleData>
    </FormAction>
    <FormAction xsi:type="EndConditionAction">
      <FormIdentity>
        <Id>BE9F56EA0F3D47EB8ACE375A258B9C38</Id>
        <AutomaticallyPopulate>false</AutomaticallyPopulate>
        <Name>t11_Verification</Name>
        <Version>0</Version>
      </FormIdentity>
      <Identity>
        <Id>E1BFF82903874C48843D2A8BAC1014B2</Id>
        <Name>endNextAssociatedFileFound</Name>
        <ActionType>EndCondition</ActionType>
      </Identity>
      <Method>
        <Parameters />
        <DupMethodNoSpecified>false</DupMethodNoSpecified>
      </Method>
      <Languages>
        <EventLanguage>
          <Id>Default</Id>
          <Language>Default</Language>
        </EventLanguage>
      </Languages>
      <Controls />
      <FiringCondition />
      <SingleActionBatch>false</SingleActionBatch>
      <IsReadOnly>false</IsReadOnly>
      <IsCapture>false</IsCapture>
      <ReturnOutputsWithoutProcessing>false</ReturnOutputsWithoutProcessing>
      <ExcludeFromVariablesDeployedForm>true</ExcludeFromVariablesDeployedForm>
    </FormAction>
    <FormAction xsi:type="BeginConditionAction">
      <FormIdentity>
        <Id>BE9F56EA0F3D47EB8ACE375A258B9C38</Id>
        <AutomaticallyPopulate>false</AutomaticallyPopulate>
        <Name>t11_Verification</Name>
        <Version>0</Version>
      </FormIdentity>
      <Identity>
        <Id>B2B7E2B42C0C486FA9113FBE603BC4C3</Id>
        <Name>beginNextAssociatedFileNotFound</Name>
        <ActionType>BeginCondition</ActionType>
      </Identity>
      <Method>
        <Parameters />
        <DupMethodNoSpecified>false</DupMethodNoSpecified>
      </Method>
      <Languages>
        <EventLanguage>
          <Id>Default</Id>
          <Language>Default</Language>
        </EventLanguage>
      </Languages>
      <Controls />
      <FiringCondition>
        <Condition>
          <Id>AssociatedFile</Id>
          <Operator>EQUALS</Operator>
          <Value>""</Value>
          <Source>Inline</Source>
          <ControlType>FormVariable</ControlType>
          <FieldType>String</FieldType>
        </Condition>
      </FiringCondition>
      <SingleActionBatch>false</SingleActionBatch>
      <IsReadOnly>false</IsReadOnly>
      <IsCapture>false</IsCapture>
      <ReturnOutputsWithoutProcessing>false</ReturnOutputsWithoutProcessing>
      <ExcludeFromVariablesDeployedForm>true</ExcludeFromVariablesDeployedForm>
      <RuleData>
        <RuleInputs>
          <RuleInput>
            <Id>AssociatedFile</Id>
            <Scope>FormVariable</Scope>
            <VariableType>String</VariableType>
          </RuleInput>
        </RuleInputs>
        <Script>AssociatedFile = ""</Script>
        <RuleType>BeingConditionAction</RuleType>
      </RuleData>
    </FormAction>
    <FormAction xsi:type="EndConditionAction">
      <FormIdentity>
        <Id>BE9F56EA0F3D47EB8ACE375A258B9C38</Id>
        <AutomaticallyPopulate>false</AutomaticallyPopulate>
        <Name>t11_Verification</Name>
        <Version>0</Version>
      </FormIdentity>
      <Identity>
        <Id>A0D4DF3805894E688F15A64273F7C982</Id>
        <Name>endNextAssociatedFileNotFound</Name>
        <ActionType>EndCondition</ActionType>
      </Identity>
      <Method>
        <Parameters />
        <DupMethodNoSpecified>false</DupMethodNoSpecified>
      </Method>
      <Languages>
        <EventLanguage>
          <Id>Default</Id>
          <Language>Default</Language>
        </EventLanguage>
      </Languages>
      <Controls />
      <FiringCondition />
      <SingleActionBatch>false</SingleActionBatch>
      <IsReadOnly>false</IsReadOnly>
      <IsCapture>false</IsCapture>
      <ReturnOutputsWithoutProcessing>false</ReturnOutputsWithoutProcessing>
      <ExcludeFromVariablesDeployedForm>true</ExcludeFromVariablesDeployedForm>
    </FormAction>
    <FormAction xsi:type="RedirectAction">
      <FormIdentity>
        <Id>BE9F56EA0F3D47EB8ACE375A258B9C38</Id>
        <AutomaticallyPopulate>false</AutomaticallyPopulate>
        <Name>t11_Verification</Name>
        <Version>0</Version>
      </FormIdentity>
      <Identity>
        <Id>34471E2BF07B428AA3BA8608AE920057</Id>
        <Name>redirectToGenericTakeActivity</Name>
        <ActionType>Redirect</ActionType>
      </Identity>
      <Method>
        <Parameters />
        <DupMethodNoSpecified>false</DupMethodNoSpecified>
      </Method>
      <Languages>
        <EventLanguage>
          <Id>Default</Id>
          <Language>Default</Language>
        </EventLanguage>
      </Languages>
      <Controls />
      <FiringCondition />
      <SingleActionBatch>false</SingleActionBatch>
      <IsReadOnly>false</IsReadOnly>
      <IsCapture>false</IsCapture>
      <ReturnOutputsWithoutProcessing>false</ReturnOutputsWithoutProcessing>
      <ExcludeFromVariablesDeployedForm>true</ExcludeFromVariablesDeployedForm>
      <Redirect>
        <IsModalWindow>false</IsModalWindow>
        <Page>TakeActivity.form?jobid=sppJOB_ID&amp;epc=sppEPC&amp;nodeid=sppNODE_ID</Page>
        <Target>SameWindow</Target>
        <RedirectType>Dynamic</RedirectType>
        <PopupWidth>0</PopupWidth>
        <PopupHeight>0</PopupHeight>
        <IgnoreRedirectConfirmation>true</IgnoreRedirectConfirmation>
        <UseBreadcrumbTrail>false</UseBreadcrumbTrail>
      </Redirect>
    </FormAction>
    <FormAction xsi:type="DotNetAction">
      <FormIdentity>
        <Id>BE9F56EA0F3D47EB8ACE375A258B9C38</Id>
        <AutomaticallyPopulate>false</AutomaticallyPopulate>
        <Name>t11_Verification</Name>
        <Version>0</Version>
      </FormIdentity>
      <Identity>
        <Id>EB6360B97F5846B88F266FC87E699E36</Id>
        <Name>VerificationControlRejectDocumentsAction</Name>
        <ActionType>DotNet</ActionType>
      </Identity>
      <Method>
        <Name>RejectDocuments</Name>
        <ClassName>TotalAgility.Sdk.CaptureRuntimeService</ClassName>
        <AssemblyName>TotalAgility.Sdk.dll</AssemblyName>
        <AssemblyLoadType>File</AssemblyLoadType>
        <Parameters>
          <Parameter direction="in" source="session" field="SESSION_ID" datatype="System.String" value="" name="sessionId" selection="false" />
          <Parameter direction="in" source="" field="" datatype="Agility.Sdk.Model.Capture.CommonInfo" value="" name="commonInfo" selection="false">
            <member name="BatchId" source="formvariable" type="System.String" value="" field="BatchId" selection="false" index="0" />
            <member name="ActivityType" source="inline" type="System.Int16" value="3" field="" selection="false" index="0" />
          </Parameter>
          <Parameter direction="in" source="" field="" datatype="System.Object" name="reportingData" selection="false" />
          <Parameter direction="in" source="form" field="VerificationControl.batchEditOperation.selectedDocuments" datatype="System.Object" value="" name="documentIds" selection="false" />
          <Parameter direction="in" source="form" field="VerificationControl.batchEditOperation.reason" datatype="System.String" value="" name="reason" selection="false" />
          <Parameter direction="in" source="form" field="VerificationControl.batchEditOperation.changes" datatype="System.Object" value="" name="changes" selection="false" />
          <Parameter direction="ret" source="inlinescript" field="INLINESCRIPT" datatype="Kofax.CEBPM.ThinClient.DocumentServices.BatchEditResults" value="" name="Return Parameter" selection="false" />
        </Parameters>
        <AssemblyFilePath>TotalAgility.Sdk.dll</AssemblyFilePath>
        <DupMethodNo>1</DupMethodNo>
        <DupMethodNoSpecified>true</DupMethodNoSpecified>
      </Method>
      <Languages>
        <EventLanguage>
          <Id>Default</Id>
          <Language>Default</Language>
        </EventLanguage>
      </Languages>
      <Controls />
      <FiringCondition />
      <SingleActionBatch>false</SingleActionBatch>
      <IsReadOnly>true</IsReadOnly>
      <IsCapture>true</IsCapture>
      <ReturnOutputsWithoutProcessing>false</ReturnOutputsWithoutProcessing>
      <ExcludeFromVariablesDeployedForm>true</ExcludeFromVariablesDeployedForm>
    </FormAction>
    <FormAction xsi:type="DotNetAction">
      <FormIdentity>
        <Id>BE9F56EA0F3D47EB8ACE375A258B9C38</Id>
        <AutomaticallyPopulate>false</AutomaticallyPopulate>
        <Name>t11_Verification</Name>
        <Version>0</Version>
      </FormIdentity>
      <Identity>
        <Id>138B2CDC66174605A44B519FAC61C790</Id>
        <Name>VerificationControlUnrejectDocumentsAction</Name>
        <ActionType>DotNet</ActionType>
      </Identity>
      <Method>
        <Name>UnrejectDocuments</Name>
        <ClassName>TotalAgility.Sdk.CaptureRuntimeService</ClassName>
        <AssemblyName>TotalAgility.Sdk.dll</AssemblyName>
        <AssemblyLoadType>File</AssemblyLoadType>
        <Parameters>
          <Parameter direction="in" source="session" field="SESSION_ID" datatype="System.String" value="" name="sessionId" selection="false" />
          <Parameter direction="in" source="" field="" datatype="Agility.Sdk.Model.Capture.CommonInfo" value="" name="commonInfo" selection="false">
            <member name="BatchId" source="formvariable" type="System.String" value="" field="BatchId" selection="false" index="0" />
            <member name="ActivityType" source="inline" type="System.Int16" value="3" field="" selection="false" index="0" />
          </Parameter>
          <Parameter direction="in" source="" field="" datatype="System.Object" name="reportingData" selection="false" />
          <Parameter direction="in" source="form" field="VerificationControl.batchEditOperation.selectedDocuments" datatype="System.Object" value="" name="documentIds" selection="false" />
          <Parameter direction="in" source="form" field="VerificationControl.batchEditOperation.changes" datatype="System.Object" value="" name="changes" selection="false" />
          <Parameter direction="ret" source="inlinescript" field="INLINESCRIPT" datatype="Kofax.CEBPM.ThinClient.DocumentServices.BatchEditResults" value="" name="Return Parameter" selection="false" />
        </Parameters>
        <AssemblyFilePath>TotalAgility.Sdk.dll</AssemblyFilePath>
        <DupMethodNo>1</DupMethodNo>
        <DupMethodNoSpecified>true</DupMethodNoSpecified>
      </Method>
      <Languages>
        <EventLanguage>
          <Id>Default</Id>
          <Language>Default</Language>
        </EventLanguage>
      </Languages>
      <Controls />
      <FiringCondition />
      <SingleActionBatch>false</SingleActionBatch>
      <IsReadOnly>true</IsReadOnly>
      <IsCapture>true</IsCapture>
      <ReturnOutputsWithoutProcessing>false</ReturnOutputsWithoutProcessing>
      <ExcludeFromVariablesDeployedForm>true</ExcludeFromVariablesDeployedForm>
    </FormAction>
    <FormAction xsi:type="DotNetAction">
      <FormIdentity>
        <Id>BE9F56EA0F3D47EB8ACE375A258B9C38</Id>
        <AutomaticallyPopulate>false</AutomaticallyPopulate>
        <Name>t11_Verification</Name>
        <Version>0</Version>
      </FormIdentity>
      <Identity>
        <Id>FE9DA895D1B0463599239C57E02FBF7C</Id>
        <Name>VerificationControlRejectPagesAction</Name>
        <ActionType>DotNet</ActionType>
      </Identity>
      <Method>
        <Name>RejectPages</Name>
        <ClassName>TotalAgility.Sdk.CaptureRuntimeService</ClassName>
        <AssemblyName>TotalAgility.Sdk.dll</AssemblyName>
        <AssemblyLoadType>File</AssemblyLoadType>
        <Parameters>
          <Parameter direction="in" source="session" field="SESSION_ID" datatype="System.String" value="" name="sessionId" selection="false" />
          <Parameter direction="in" source="" field="" datatype="Agility.Sdk.Model.Capture.CommonInfo" value="" name="commonInfo" selection="false">
            <member name="BatchId" source="formvariable" type="System.String" value="" field="BatchId" selection="false" index="0" />
            <member name="ActivityType" source="inline" type="System.Int16" value="3" field="" selection="false" index="0" />
          </Parameter>
          <Parameter direction="in" source="form" field="VerificationControl.batchEditOperation.currentDocument" datatype="System.String" value="" name="documentId" selection="false" />
          <Parameter direction="in" source="form" field="VerificationControl.batchEditOperation.selectedPages" datatype="System.Object" value="" name="pageIndexes" selection="false" />
          <Parameter direction="in" source="form" field="VerificationControl.batchEditOperation.rejectionNote" datatype="System.String" value="" name="reason" selection="false" />
          <Parameter direction="in" source="form" field="VerificationControl.batchEditOperation.changes" datatype="System.Object" value="" name="changes" selection="false" />
          <Parameter direction="ret" source="inlinescript" field="INLINESCRIPT" datatype="Kofax.CEBPM.ThinClient.DocumentServices.BatchEditResults" value="" name="Return Parameter" selection="false" />
        </Parameters>
        <AssemblyFilePath>TotalAgility.Sdk.dll</AssemblyFilePath>
        <DupMethodNo>1</DupMethodNo>
        <DupMethodNoSpecified>true</DupMethodNoSpecified>
      </Method>
      <Languages>
        <EventLanguage>
          <Id>Default</Id>
          <Language>Default</Language>
        </EventLanguage>
      </Languages>
      <Controls />
      <FiringCondition />
      <SingleActionBatch>false</SingleActionBatch>
      <IsReadOnly>true</IsReadOnly>
      <IsCapture>true</IsCapture>
      <ReturnOutputsWithoutProcessing>false</ReturnOutputsWithoutProcessing>
      <ExcludeFromVariablesDeployedForm>true</ExcludeFromVariablesDeployedForm>
    </FormAction>
    <FormAction xsi:type="DotNetAction">
      <FormIdentity>
        <Id>BE9F56EA0F3D47EB8ACE375A258B9C38</Id>
        <AutomaticallyPopulate>false</AutomaticallyPopulate>
        <Name>t11_Verification</Name>
        <Version>0</Version>
      </FormIdentity>
      <Identity>
        <Id>10BD62AB2CA1453CB9197F078728345A</Id>
        <Name>VerificationControlUnrejectPagesAction</Name>
        <ActionType>DotNet</ActionType>
      </Identity>
      <Method>
        <Name>UnrejectPages</Name>
        <ClassName>TotalAgility.Sdk.CaptureRuntimeService</ClassName>
        <AssemblyName>TotalAgility.Sdk.dll</AssemblyName>
        <AssemblyLoadType>File</AssemblyLoadType>
        <Parameters>
          <Parameter direction="in" source="session" field="SESSION_ID" datatype="System.String" value="" name="sessionId" selection="false" />
          <Parameter direction="in" source="" field="" datatype="Agility.Sdk.Model.Capture.CommonInfo" value="" name="commonInfo" selection="false">
            <member name="BatchId" source="formvariable" type="System.String" value="" field="BatchId" selection="false" index="0" />
            <member name="ActivityType" source="inline" type="System.Int16" value="3" field="" selection="false" index="0" />
          </Parameter>
          <Parameter direction="in" source="form" field="VerificationControl.batchEditOperation.currentDocument" datatype="System.String" value="" name="documentId" selection="false" />
          <Parameter direction="in" source="form" field="VerificationControl.batchEditOperation.selectedPages" datatype="System.Object" value="" name="pageIndexes" selection="false" />
          <Parameter direction="in" source="form" field="VerificationControl.batchEditOperation.changes" datatype="System.Object" value="" name="changes" selection="false" />
          <Parameter direction="ret" source="inlinescript" field="INLINESCRIPT" datatype="Kofax.CEBPM.ThinClient.DocumentServices.BatchEditResults" value="" name="Return Parameter" selection="false" />
        </Parameters>
        <AssemblyFilePath>TotalAgility.Sdk.dll</AssemblyFilePath>
        <DupMethodNo>1</DupMethodNo>
        <DupMethodNoSpecified>true</DupMethodNoSpecified>
      </Method>
      <Languages>
        <EventLanguage>
          <Id>Default</Id>
          <Language>Default</Language>
        </EventLanguage>
      </Languages>
      <Controls />
      <FiringCondition />
      <SingleActionBatch>false</SingleActionBatch>
      <IsReadOnly>true</IsReadOnly>
      <IsCapture>true</IsCapture>
      <ReturnOutputsWithoutProcessing>false</ReturnOutputsWithoutProcessing>
      <ExcludeFromVariablesDeployedForm>true</ExcludeFromVariablesDeployedForm>
    </FormAction>
    <FormAction xsi:type="DotNetAction">
      <FormIdentity>
        <Id>BE9F56EA0F3D47EB8ACE375A258B9C38</Id>
        <AutomaticallyPopulate>false</AutomaticallyPopulate>
        <Name>t11_Verification</Name>
        <Version>0</Version>
      </FormIdentity>
      <Identity>
        <Id>3003F2FA25194EF4897BB4DDDB8BEA1A</Id>
        <Name>SaveChanges</Name>
        <ActionType>DotNet</ActionType>
      </Identity>
      <Method>
        <Name>SaveChanges2</Name>
        <ClassName>TotalAgility.Sdk.CaptureRuntimeService</ClassName>
        <AssemblyName>TotalAgility.Sdk.dll</AssemblyName>
        <AssemblyLoadType>File</AssemblyLoadType>
        <Parameters>
          <Parameter direction="in" source="session" field="SESSION_ID" datatype="System.String" value="" name="sessionId" selection="false" />
          <Parameter direction="in" source="" field="" datatype="Agility.Sdk.Model.Capture.CommonInfo" value="" name="commonInfo" selection="false">
            <member name="BatchId" source="inlinescript" type="System.String" value="" field="CEBPM.controller.AppConfig.getMainView().sessionID" selection="false" index="0" />
            <member name="ActivityType" source="inline" type="System.Int16" value="3" field="" selection="false" index="0" />
          </Parameter>
          <Parameter direction="in" source="inlinescript" field="CEBPM.controller.BatchData.getChanges()" datatype="System.Object" value="" name="changes" selection="false" />
          <Parameter direction="ret" source="inlinescript" field="INLINESCRIPT" datatype="Kofax.CEBPM.ThinClient.DocumentServices.ValidationDataContainer" value="" name="Return Parameter" selection="false" />
        </Parameters>
        <AssemblyFilePath>TotalAgility.Sdk.dll</AssemblyFilePath>
        <DupMethodNo>1</DupMethodNo>
        <DupMethodNoSpecified>true</DupMethodNoSpecified>
      </Method>
      <Languages>
        <EventLanguage>
          <Id>Default</Id>
          <Language>Default</Language>
        </EventLanguage>
      </Languages>
      <Controls />
      <FiringCondition />
      <SingleActionBatch>false</SingleActionBatch>
      <IsReadOnly>true</IsReadOnly>
      <IsCapture>true</IsCapture>
      <ReturnOutputsWithoutProcessing>true</ReturnOutputsWithoutProcessing>
      <ExcludeFromVariablesDeployedForm>true</ExcludeFromVariablesDeployedForm>
    </FormAction>
  </Actions>
  <FormVariables>
    <FormVariable>
      <Identity>
        <Name>BatchId</Name>
      </Identity>
      <VariableType xsi:type="xsd:string">String</VariableType>
      <Value xsi:type="xsd:string" />
    </FormVariable>
    <FormVariable>
      <Identity>
        <Name>DocumentId</Name>
      </Identity>
      <VariableType xsi:type="xsd:string">String</VariableType>
      <Value xsi:type="xsd:string" />
    </FormVariable>
    <FormVariable>
      <Identity>
        <Name>FolderId</Name>
      </Identity>
      <VariableType xsi:type="xsd:string">String</VariableType>
      <Value xsi:type="xsd:string" />
    </FormVariable>
    <FormVariable>
      <Identity>
        <Name>sppEPC</Name>
      </Identity>
      <VariableType xsi:type="xsd:string">Numeric</VariableType>
      <Value xsi:type="xsd:int">0</Value>
    </FormVariable>
    <FormVariable>
      <Identity>
        <Name>sppJOB_ID</Name>
      </Identity>
      <VariableType xsi:type="xsd:string">String</VariableType>
      <Value xsi:type="xsd:string" />
    </FormVariable>
    <FormVariable>
      <Identity>
        <Name>sppNODE_ID</Name>
      </Identity>
      <VariableType xsi:type="xsd:string">Numeric</VariableType>
      <Value xsi:type="xsd:int">0</Value>
    </FormVariable>
    <FormVariable>
      <Identity>
        <Name>sppSESSION_ID</Name>
      </Identity>
      <VariableType xsi:type="xsd:string">String</VariableType>
      <Value xsi:type="xsd:string" />
    </FormVariable>
    <FormVariable>
      <Identity>
        <Name>sppACTIVITY_NAME</Name>
      </Identity>
      <VariableType xsi:type="xsd:string">String</VariableType>
      <Value xsi:type="xsd:string" />
    </FormVariable>
    <FormVariable>
      <Identity>
        <Name>AssociatedFile</Name>
      </Identity>
      <VariableType xsi:type="xsd:string">String</VariableType>
      <Value xsi:type="xsd:string" />
    </FormVariable>
    <FormVariable>
      <Identity>
        <Name>FoundActivity</Name>
      </Identity>
      <VariableType xsi:type="xsd:string">Boolean</VariableType>
      <Value xsi:type="xsd:boolean">false</Value>
    </FormVariable>
  </FormVariables>
  <CategoryId>201F370CA5164F76ADDD8EEEFF666AF7</CategoryId>
  <UseHeader xsi:nil="true" />
  <UseHorizontalNavigation xsi:nil="true" />
  <UseVerticalNavigation xsi:nil="true" />
  <StringMappingsCollection>
    <StringMappingEntity>
      <ControlID>BE9F56EA0F3D47EB8ACE375A258B9C38</ControlID>
      <Property>formtitle</Property>
      <StringId>DEA2BDC57AFA4A28B8BF303408BA73C4</StringId>
    </StringMappingEntity>
    <StringMappingEntity>
      <ControlID>B49D2342D884466C81470744D47F6C62</ControlID>
      <Property>titletext</Property>
      <StringId>7AE6BCE0047C4F4681D8A346F50A58FC</StringId>
    </StringMappingEntity>
    <StringMappingEntity>
      <ControlID>C7DBA2E6031448F492445F5014CD44F0</ControlID>
      <Property>DocumentDisplayText</Property>
      <StringId>FFA45E456C774DDAA69072064412458E</StringId>
    </StringMappingEntity>
    <StringMappingEntity>
      <ControlID>C7DBA2E6031448F492445F5014CD44F0</ControlID>
      <Property>FolderDisplayText</Property>
      <StringId>DB8E7631014449C792347F26BA8F8D8A</StringId>
    </StringMappingEntity>
    <StringMappingEntity>
      <ControlID>C7DBA2E6031448F492445F5014CD44F0</ControlID>
      <Property>ProcessDisplayText</Property>
      <StringId>054B4F07D9F54E7FB578D9014FCC0CE1</StringId>
    </StringMappingEntity>
    <StringMappingEntity>
      <StringId>DA40FC106BB24DEBB673359402AB3678</StringId>
      <VarId>BatchId</VarId>
    </StringMappingEntity>
    <StringMappingEntity>
      <StringId>6D3FFE47A1B645EA99DB3200A5A36B9B</StringId>
      <VarId>DocumentId</VarId>
    </StringMappingEntity>
    <StringMappingEntity>
      <StringId>7AC540767F5341F29338A19B5900C25B</StringId>
      <VarId>FolderId</VarId>
    </StringMappingEntity>
    <StringMappingEntity>
      <StringId>026AAE4F2EFD4822AEBC60868EB2723D</StringId>
      <VarId>sppJOB_ID</VarId>
    </StringMappingEntity>
    <StringMappingEntity>
      <StringId>74A7518ADDE44441BB59FC027E976657</StringId>
      <VarId>sppSESSION_ID</VarId>
    </StringMappingEntity>
    <StringMappingEntity>
      <StringId>E7E1348C9C894F65B2CDA99FC60D3C70</StringId>
      <VarId>sppACTIVITY_NAME</VarId>
    </StringMappingEntity>
    <StringMappingEntity>
      <StringId>78B7DB669FB84561BCFA3BCE1E845258</StringId>
      <VarId>AssociatedFile</VarId>
    </StringMappingEntity>
  </StringMappingsCollection>
  <Language>base</Language>
  <DisplayRules />
  <CalculationRules />
  <LockedBy>
    <Id>EF125000ED0B4FDDA1E4CE6343503603</Id>
    <AutomaticallyPopulate>true</AutomaticallyPopulate>
    <Name />
    <ResourceType>Worker</ResourceType>
    <EmailAddress />
    <UserId />
    <ManagerialLevel>0</ManagerialLevel>
  </LockedBy>
  <RefreshInterval>0</RefreshInterval>
  <BackgroundColor>#FFFFFFFF</BackgroundColor>
  <ErrorLocation>Default</ErrorLocation>
  <FormLayout>Flow</FormLayout>
  <PercentageWidth>100</PercentageWidth>
  <Status>Released</Status>
  <ApplySecurityToken>false</ApplySecurityToken>
  <AllowByDefault>true</AllowByDefault>
  <Resources />
  <FormEvents>
    <FormEvent>
      <EventType>OnVerificationFormLoaded</EventType>
      <Actions>
        <FormActionSummary>
          <Identity>
            <Id>D17E1B4E93A8430788EEA70C629FB0DD</Id>
            <Name>takependingactivity</Name>
            <ActionType>DotNet</ActionType>
          </Identity>
          <Disabled>false</Disabled>
        </FormActionSummary>
        <FormActionSummary>
          <Identity>
            <Id>9499B9CD17434A128AFDE5B912409AA5</Id>
            <Name>VerificationControlLoadBatchAction</Name>
            <ActionType>DotNet</ActionType>
          </Identity>
          <Disabled>false</Disabled>
        </FormActionSummary>
      </Actions>
    </FormEvent>
    <FormEvent>
      <EventType>BeforeRender</EventType>
      <Actions />
    </FormEvent>
    <FormEvent>
      <EventType>AfterRender</EventType>
      <Actions />
    </FormEvent>
  </FormEvents>
  <IsThemePageColor>true</IsThemePageColor>
  <ShouldTriggerOnLoad>false</ShouldTriggerOnLoad>
  <FormGenerationSettings>
    <Identity>
      <Id>BAC28B19EC0D44D3A757CC4DFDBC6E1A</Id>
      <AutomaticallyPopulate>true</AutomaticallyPopulate>
      <Version>1</Version>
      <Name>t11</Name>
    </Identity>
    <NodeIdentity>
      <Id>6</Id>
      <SubNodeId>0</SubNodeId>
      <Name>Verification</Name>
      <NodeType>VerificationCaptureActivity</NodeType>
    </NodeIdentity>
    <UpdateAssociatedFile>false</UpdateAssociatedFile>
    <AssociatedFileName />
    <UseManualLogon>false</UseManualLogon>
    <UsePassword>false</UsePassword>
    <LogOnFormType>NotSet</LogOnFormType>
  </FormGenerationSettings>
  <AssociatedLabelWidth>0</AssociatedLabelWidth>
  <UseViewport>false</UseViewport>
  <BackgroundSettings>
    <UseBackgroundImage>false</UseBackgroundImage>
    <LoadImageFromStore>false</LoadImageFromStore>
    <ResizeImageToFit>false</ResizeImageToFit>
  </BackgroundSettings>
  <FormAlign>Center</FormAlign>
  <TouchEnabled>false</TouchEnabled>
  <MobileFormProperties>
    <ActionMenus />
  </MobileFormProperties>
  <NavigationView>
    <ToolBars />
    <Enabled>false</Enabled>
  </NavigationView>
  <DesignWidth>1300</DesignWidth>
  <DesignHeight>0</DesignHeight>
  <PrimaryForm>Desktop</PrimaryForm>
  <AllowAnyone>true</AllowAnyone>
  <ResourceAccessTokens>
    <ResourceAccess>
      <ResourceIdentity>
        <Id>7DF43CCDF24611D2804B00104B71BD15</Id>
        <AutomaticallyPopulate>true</AutomaticallyPopulate>
        <Name>Everyone</Name>
        <ResourceType>GroupOfWorkers</ResourceType>
        <EmailAddress />
        <UserId />
        <ManagerialLevel>0</ManagerialLevel>
      </ResourceIdentity>
      <AccessType>MaintenanceAccess</AccessType>
      <PermissionType>FullControl</PermissionType>
    </ResourceAccess>
  </ResourceAccessTokens>
  <ResourcePermissionType>FullControl</ResourcePermissionType>
  <RedirectConfirmation>true</RedirectConfirmation>
  <RedirectOnLoadErrorForm>
    <FormIdentity>
      <Id />
      <AutomaticallyPopulate>true</AutomaticallyPopulate>
      <Version>0</Version>
    </FormIdentity>
    <RedirectOptions>Origin</RedirectOptions>
  </RedirectOnLoadErrorForm>
  <FormVariants />
  <UseBrowserTabOrder>true</UseBrowserTabOrder>
  <EnableColumnSplitting>false</EnableColumnSplitting>
  <ShowColumnSplitter>false</ShowColumnSplitter>
  <ExpandLastRowToFit>true</ExpandLastRowToFit>
  <UseRelativeHeight>true</UseRelativeHeight>
  <Responsive>false</Responsive>
  <ShowMandatoryAsterisk>true</ShowMandatoryAsterisk>
  <FormDataModels />
  <MappedFormVariables />
  <GetQueriesAssociatedWithFormVariants />
  <OverrideTableRowsAutoHeight>None</OverrideTableRowsAutoHeight>
</CaptureVerificationActivityForm>